pyedi/__init__.py
pyedi/code_sets/__init__.py
pyedi/code_sets/edi_codes.py
pyedi/core/__init__.py
pyedi/core/map_loader.py
pyedi/core/mapper.py
pyedi/core/parser.py
pyedi/core/segment_handlers.py
pyedi/core/structured_formatter.py
pyedi/pipelines/__init__.py
pyedi/pipelines/transform_pipeline.py
pyedi-1.1.0.dist-info/licenses/LICENSE
pyedi-1.1.0.dist-info/METADATA
pyedi-1.1.0.dist-info/WHEEL
pyedi-1.1.0.dist-info/entry_points.txt
pyedi-1.1.0.dist-info/top_level.txt
pyedi-1.1.0.dist-info/RECORD
