Metadata-Version: 2.4
Name: pyedi
Version: 1.1.0
Summary: A comprehensive Python package for parsing, transforming, and mapping X12 EDI files
Home-page: https://github.com/jaymd96/pyedi
Author: James
Author-email: 
Maintainer: James
License: MIT
Project-URL: Homepage, https://github.com/jaymd96/pyedi
Project-URL: Documentation, https://pyedi.readthedocs.io
Project-URL: Repository, https://github.com/jaymd96/pyedi
Project-URL: Bug Tracker, https://github.com/jaymd96/pyedi/issues
Keywords: x12,edi,healthcare,parser,transformer,jsonata,835,837,834,electronic-data-interchange
Classifier: Development Status :: 4 - Beta
Classifier: Intended Audience :: Developers
Classifier: Intended Audience :: Healthcare Industry
Classifier: License :: OSI Approved :: MIT License
Classifier: Programming Language :: Python :: 3
Classifier: Programming Language :: Python :: 3.8
Classifier: Programming Language :: Python :: 3.9
Classifier: Programming Language :: Python :: 3.10
Classifier: Programming Language :: Python :: 3.11
Classifier: Programming Language :: Python :: 3.12
Classifier: Topic :: Software Development :: Libraries :: Python Modules
Classifier: Topic :: Text Processing :: Markup
Classifier: Topic :: Office/Business :: Financial
Requires-Python: >=3.8
License-File: LICENSE
Requires-Dist: pyx12>=2.3.3
Requires-Dist: jsonata-python>=0.6.0
Provides-Extra: cli
Requires-Dist: click>=8.0; extra == "cli"
Requires-Dist: colorama>=0.4.4; extra == "cli"
Provides-Extra: dev
Requires-Dist: pytest>=7.0; extra == "dev"
Requires-Dist: pytest-cov>=4.0; extra == "dev"
Requires-Dist: black>=22.0; extra == "dev"
Requires-Dist: flake8>=5.0; extra == "dev"
Requires-Dist: mypy>=1.0; extra == "dev"
Requires-Dist: pre-commit>=3.0; extra == "dev"
Provides-Extra: docs
Requires-Dist: sphinx>=5.0; extra == "docs"
Requires-Dist: sphinx-rtd-theme>=1.0; extra == "docs"
Dynamic: home-page
Dynamic: license-file
Dynamic: requires-python
